fastapi_cacher/__init__.py
fastapi_cacher/base.py
fastapi_cacher/coder.py
fastapi_cacher/config.py
fastapi_cacher/utils.py
fastapi_cacher/backends/__init__.py
fastapi_cacher/backends/dynamodb.py
fastapi_cacher/backends/memcache.py
fastapi_cacher/backends/mongocache.py
fastapi_cacher/backends/rediscache.py
fastapi_cacher/backends/simplecache.py
tests/__init__.py
tests/test_codecs.py
fastapi_cacher-0.3.3.dist-info/LICENSE
fastapi_cacher-0.3.3.dist-info/METADATA
fastapi_cacher-0.3.3.dist-info/WHEEL
fastapi_cacher-0.3.3.dist-info/top_level.txt
fastapi_cacher-0.3.3.dist-info/RECORD
