Metadata-Version: 2.1
Name: fastapi-cacher
Version: 0.3.3
Summary: A caching library for FastAPI
Home-page: https://github.com/Fahadukr/fastapi-cacher
Author: Fahad Mawlood
Author-email: fahadukr@gmail.com
License: UNKNOWN
Platform: UNKNOWN
Classifier: Programming Language :: Python :: 3
Classifier: License :: OSI Approved :: MIT License
Classifier: Operating System :: OS Independent
Requires-Python: >=3.10
Requires-Dist: fastapi
Requires-Dist: redis
Requires-Dist: cachelib
Requires-Dist: motor
Requires-Dist: pendulum
Requires-Dist: pymongo
Requires-Dist: aiomcache
